tensor_repr/__init__.py
tensor_repr-0.2.1.dist-info/LICENSE
tensor_repr-0.2.1.dist-info/METADATA
tensor_repr-0.2.1.dist-info/WHEEL
tensor_repr-0.2.1.dist-info/top_level.txt
tensor_repr-0.2.1.dist-info/RECORD
